schemafy.py
SparkSchemafy-0.1.4.dist-info/LICENSE.txt
SparkSchemafy-0.1.4.dist-info/METADATA
SparkSchemafy-0.1.4.dist-info/WHEEL
SparkSchemafy-0.1.4.dist-info/top_level.txt
SparkSchemafy-0.1.4.dist-info/RECORD
